{
  "gitbook": "3.1.0",
  "title": "Controlled Forms for React and Redux",
  "author": "Robin Frischmann <robin@rofrischmann.de>",
  "description": "Official documentation for react-controlled-form",
  "language": "en",
  "plugins": [
    "edit-link",
    "prism",
    "-highlight",
    "github",
    "anker-enable",
    "advanced-emoji"
  ],
  "pluginsConfig": {
    "edit-link": {
      "base": "https://github.com/rofrischmann/react-controlled-form/tree/master",
      "label": "Edit This Page"
    },
    "github": {
      "url": "https://github.com/rofrischmann/react-controlled-form/"
    }
  }
}
